{
    "strategy_name": "strategy_opt_6",
    "trial_number": 4,
    "symbol": "sol",
    "time_horizon": "5m",
    "pnl_sum": 31.07342430062554,
    "optimized_params": {
        "sma_window": 44,
        "ema_window": 21,
        "wma_window": 7,
        "dema_window": 10,
        "tema_window": 21,
        "trima_window": 22,
        "kama_window": 10,
        "t3_window": 11,
        "midpoint_window": 11,
        "bbands_window": 21,
        "adx_window": 18,
        "adxr_window": 7,
        "aroon_window": 13,
        "aroonosc_window": 25,
        "cci_window": 22,
        "cmo_window": 28,
        "dx_window": 24,
        "mfi_window": 27,
        "minus_di_window": 23,
        "minus_dm_window": 16,
        "plus_di_window": 21,
        "plus_dm_window": 14,
        "rsi_window": 26,
        "trix_window": 12,
        "willr_window": 30,
        "atr_window": 7,
        "natr_window": 13,
        "trange_window": 21,
        "tp": 0.0455337957228221,
        "sl": 0.042662955742542884
    }
}